Workbook

Sheet Employee salary
A1: Tên đơn vị: | C1: CTY TNHH SEALINK INTERNATIONAL
A2: Địa chỉ: | C2: Tầng 4, CC Copac Squre, Số 12 Tôn Đản, P.13, Q.4, TP.HCM
A3: MST: | C3: 0317388504 | F3: BẢNG LƯƠNG NHÂN VIÊN/ EMPLOYEE'S PAYROLL
A4: TPKT: | C4: CTY TNHH 100% Vốn nước ngoài | G4: 22 | K4: THÁNG/MONTH: | Q4: 05 | R4: 2026
A7: STT | B7: Ngày công thực tế / Actual working day | C7: Họ và tên /Fullname | D7: Số phụ thuộc | E7: Vị trí | F7: Mức Lương HĐLĐ | G7: Mức lương thực trong tháng | H7: Phụ cấp / Allowance | N7: Bonus | O7: Lương tháng 14 năm 2025 /Bonus Salary (50%) | P7: Lương nộp BHXH Salary applied for Social insurance | Q7: Trách nhiệm người lao động Payments paid by Employee | U7: Trách nhiệm người sử dụng lao động Payments paid by Employer | Z7: Tổng thu nhập trả cho cá nhân (Chịu thuế) Total income paid to personal (Taxable) | AA7: Thu nhập tính thuế Assesable income | AB7: Thuế thu nhập cá nhân Personal income tax (PIT) | AC7: Lương nhân viên thực nhận (NET Salary) | AD7: Đoàn Phí 0.5% (Union fee 0.5%) | AE7: Khấu trừ khác | AF7: Hoàn thuế PIT 2023 Refund PIT 2023 | AG7: Tổng chuyển (Transfer) | AH7: Đã chuyển, tạm ứng (Advance payment) | AI7: Phần còn lại chuyển (Rest Transferred) | AJ7: Lương tối thiểu chung | AK7: Lương tối đa đóng BHXH, BHYT | AL7: BHXH | AM7: BHYT | AN7: BHTN | AO7: Trách nhiệm BH | AP7: Giảm trừ bản thân | AQ7: Giảm trừ người phụ thuộc | AR7: Khấu trừ trực tiếp (HD thử việc)
D8: dependents | E8: Position | F8: Contract salary | G8: Actual salary | H8: Phụ cấp cơm trưa miển thuế/ Allowance meal tax free | I8: Phụ cấp cơm có thuế / Taxable meal allowance | J8: Phụ cấp điện thoại miển thuế/ Allowance telephone tax free | K8: Phụ cấp xăng xe tính thuế/ Taxable transport allowance | L8: Phụ cấp hiệu quả công việc tính thuế / Taxable Performance allowance | M8: Khác/ Other | Q8: BHXH 8% (Social Insu. 8%) | R8: BHYT 1.5% (Health Insu. 1.5%) | S8: BHTN 1% (Unemploy. Insu. 1%) | T8: Tổng BH (Insurance amount) | U8: BHXH 17.5% (Social Insu. 17.5%) | V8: BHYT 3% (Health Insu. 3%) | W8: BHTN 1% (Unemploy. Insu. 0%) | X8: Tổng BH (Insurance amount) | Y8: Kinh phí công đoàn 2% (Union funds 2%) | AJ8: 2340000 | AK8: =AJ8*20 -> 46800000 | AL8: 0.08 | AM8: 0.015 | AN8: 0.01 | AO8: =SUM(AL8:AN8) -> 0.105 | AP8: 11000000 | AQ8: 4400000 | AR8: 0.1
F9: VND | G9: VND | H9: VND | J9: VND | K9: VND | M9: VND | N9: VND | O9: VND | P9: VND | Q9: VND | R9: VND | S9: VND | T9: VND | U9: VND | V9: VND | W9: VND | X9: VND | Z9: VND | AA9: VND | AB9: VND | AC9: VND | AF9: VND | AG9: VND | AH9: VND | AI9: VND
A10: A. NHÂN VIÊN CÓ HỢP ĐỒNG LAO ĐỘNG/ EMPLOYEE WITH LABOR CONTRACT | AJ10: Lương tối thiểu vùng | AK10: Lương tối đa đóng BHTN
A11: 2 | B11: 22 | C11: Nguyễn Lý Tưởng | D11: 3 | E11: Kế toán trưởng | F11: 50000 | G11: =ROUND($F11/$G$4*$B11,0) -> 50000 | H11: =ROUND(1200000/$G$4*$B11,0) -> 1200000 | J11: =ROUND(2000000/$G$4*$B11,0) -> 2000000 | K11: =ROUND(2000000/$G$4*$B11,0) -> 2000000 | L11: 2450000 | P11: =F11 -> 50000 | Q11: =ROUND($P11*8/100,0) -> 4000 | R11: =ROUND($P11*1.5/100,0) -> 750 | S11: =IF((F11+M11)>106200000,(106200000*1/100),IF((F11+M11)>46800000,ROUND((F11+M11)*1/100,0),ROUND((P11)*1/100,0))) -> 500 | T11: =ROUND(Q11+R11+S11,0) -> 5250 | U11: =ROUND($P11*17.5/100,0) -> 8750 | V11: =ROUND($P11*3/100,0) -> 1500 | W11: =IF(($F11+$M11)>106200000,(106200000*1/100),IF(($F11+$M11)>48600000,ROUND(($F11+$M11)*1/100,0),ROUND(($P11)*1/100,0))) -> 500 | X11: =ROUND(U11+V11+W11,0) -> 10750 | Y11: =ROUND($P11*2/100,0) -> 1000 | Z11: =G11+I11+K11+L11+M11+N11+O11 -> 4500000 | AA11: =IF((Z11-T11-15500000-(6200000*D11))>0,(Z11-T11-15500000-(6200000*D11)),0) -> 0 | AB11: =ROUND(IF(AA11<0,0,IF(AA11>100000000,AA11*0.35-14500000,IF(AA11>60000000,AA11*0.3-9500000,IF(AA11>30000000,AA11*0.2-3500000,IF(AA11>10000000,AA11*0.1-500000,AA11*0.05))))),0) -> 0 | AC11: =ROUND(G11+H11+I11+J11+K11+L11+M11+N11+O11-T11-AB11,2) -> 7694750 | AD11: =IF((P11*0.5%)>($AJ$8*10%),$AJ$8*10%,P11*0.5%) -> 250 | AG11: =+AC11+AF11-AD11+AE11 -> 7694500 | AI11: =AG11-AH11 -> 7694500
A12: 3 | B12: 22 | C12: Đặng Quế Quyên | D12: 1 | E12: NV chứng từ | F12: 50000 | G12: =ROUND($F12/$G$4*$B12,0) -> 50000 | H12: =ROUND(1200000/$G$4*$B12,0) -> 1200000 | J12: =ROUND(1000000/$G$4*$B12,0) -> 1000000 | K12: =ROUND(1000000/$G$4*$B12,0) -> 1000000 | P12: =IF((F12+M12)>$AK$8,$AK$8,(F12+M12)) -> 50000 | Q12: =ROUND($P12*8/100,0) -> 4000 | R12: =ROUND($P12*1.5/100,0) -> 750 | S12: =IF((F12+M12)>106200000,(106200000*1/100),IF((F12+M12)>46800000,ROUND((F12+M12)*1/100,0),ROUND((P12)*1/100,0))) -> 500 | T12: =ROUND(Q12+R12+S12,0) -> 5250 | U12: =ROUND($P12*17.5/100,0) -> 8750 | V12: =ROUND($P12*3/100,0) -> 1500 | W12: =IF(($F12+$M12)>106200000,(106200000*1/100),IF(($F12+$M12)>48600000,ROUND(($F12+$M12)*1/100,0),ROUND(($P12)*1/100,0))) -> 500 | X12: =ROUND(U12+V12+W12,0) -> 10750 | Y12: =ROUND($P12*2/100,0) -> 1000 | Z12: =G12+I12+K12+L12+M12+N12+O12 -> 1050000 | AA12: =IF((Z12-T12-15500000-(6200000*D12))>0,(Z12-T12-15500000-(6200000*D12)),0) -> 0 | AB12: =ROUND(IF(AA12<0,0,IF(AA12>100000000,AA12*0.35-14500000,IF(AA12>60000000,AA12*0.3-9500000,IF(AA12>30000000,AA12*0.2-3500000,IF(AA12>10000000,AA12*0.1-500000,AA12*0.05))))),0) -> 0 | AC12: =ROUND(G12+H12+I12+J12+K12+L12+M12+N12+O12-T12-AB12,2) -> 3244750 | AD12: =IF((P12*0.5%)>($AJ$8*10%),$AJ$8*10%,P12*0.5%) -> 250 | AG12: =+AC12+AF12-AD12+AE12 -> 3244500 | AI12: =AG12-AH12 -> 3244500
A13: Sub-total | D13: =SUM(D11:D12) -> 4 | F13: =SUM(F11:F12) -> 100000 | G13: =SUM(G11:G12) -> 100000 | H13: =SUM(H11:H12) -> 2400000 | I13: =SUM(I11:I12) -> 0 | J13: =SUM(J11:J12) -> 3000000 | K13: =SUM(K11:K12) -> 3000000 | L13: =SUM(L11:L12) -> 2450000 | M13: =SUM(M11:M12) -> 0 | ... AI13: =SUM(AI11:AI12) -> 10939000
A14: B. NHÂN VIÊN THỬ VIỆC + HỌC VIỆC / PROBATIONARY+ APPRENTICE STAFF - THUẾ 10% | AB14: Thuế suất Tax rate | AC14: 0.1
A15: 35 | B15: 21 | C15: Hồ Đăng Nhật | E15: Thử việc | F15: 50000 | G15: =ROUND((F15/$G$4)*B15,0) -> 47727 | Z15: =G15+H15+J15+K15+M15+N15+O15 -> 47727 | AA15: =G15+H15+J15+K15+M15+N15+O15 -> 47727 | AB15: =IF(AA15<=2000000,0,AA15*$AC$14) -> 0 | AC15: =ROUND(G15+H15+I15+J15+K15+M15+N15+O15-T15-AB15,2) -> 47727 | AG15: =AC15+AF15 -> 47727 | AI15: =AG15-AH15 -> 47727
A16: Sub-total | F16: =SUM(F15:F15) -> 50000 | G16: =SUM(G15:G15) -> 47727 | H16: =SUM(H15:H15) -> 0 | J16: =SUM(J15:J15) -> 0 | K16: =SUM(K15:K15) -> 0 | M16: =SUM(M15:M15) -> 0 | N16: =SUM(N15:N15) -> 0 | O16: =SUM(O15:O15) -> 0 | P16: =SUM(P15:P15) -> 0 | Q16: =SUM(Q15:Q15) -> 0 | R16: =SUM(R15:R15) -> 0 | S16: =SUM(S15:S15) -> 0 | T16: =SUM(T15:T15) -> 0 | Z16: =SUM(Z15:Z15) -> 47727 | AA16: =SUM(AA15:AA15) -> 47727 | AB16: =SUM(AB15:AB15) -> 0 | AC16: =SUM(AC15:AC15) -> 47727 | AG16: =SUM(AG15:AG15) -> 47727 | AH16: =SUM(AH15:AH15) -> 0 | AI16: =SUM(AI15:AI15) -> 47727
A18: TỔNG CỘNG | D18: =D16+D13 -> 4 | E18: =E16+E13 -> 0 | F18: =F16+F13 -> 150000 | G18: =G16+G13 -> 147727 | H18: =H16+H13 -> 2400000 | I18: =I16+I13 -> 0 | J18: =J16+J13 -> 3000000 | K18: =K16+K13 -> 3000000 | ... AB18: =AB16+AB13 -> 0 | AC18: =+AC13+AC16 -> 10987227 | AD18: =+AD13+AD16 -> 500 | AF18: =AF16+AF13 -> 0 | AG18: =+AG13+AG16 -> 10986727 | AH18: =+AH13+AH16 -> 0 | AI18: =+AI13+AI16 -> 10986727
Q20: TP.HCM, Ngày 25 tháng 05 năm 2026 | AG20: =+T18+AB18+AC18 -> 10997727
C21: LẬP BIỂU | N21: =+N18-#REF!-#REF!-2444443 -> #REF! | Q21: PHÊ DUYỆT | AC21: =+AI21-#REF! -> #REF! | AG21: =AG18 -> 10986727 | AI21: =+AI13+AI16 -> 10986727
C22: PREPARED BY | Q22: APPROVED BY
AC23: =+AC21-N22 -> #REF! | AG23: =G18+H18+I18+K18+M18+N18++J18 -> 8547727
AG24: =G18+H18+I18+J18+K18+L18+M18+N18 -> 10997727
AG25: =AG20-AG23 -> 2450000
C27: Nguyễn Lý Tưởng | U27: Tôn Thất Trung Kiên | AG27: =T18+AB18+AD18+AG21 -> 10997727
AG30: =+AG24-AG27 -> 0

Sheet Bank Transfer
B1: BANK TRANSFER - PAYROLL
B2: ='Employee salary'!C1 -> CTY TNHH SEALINK INTERNATIONAL
D3: THÁNG/MONTH | E3: ='Employee salary'!$Q$4&" "&'Employee salary'!$R$4 -> 05 2026
A4: No | B4: Full Name | C4: Net Amount | D4: Account No. | E4: Bank | F4: Pro/City | G4: Notes
C5: VND
A6: 2 | B6: Nguyễn Lý Tưởng | C6: ='Employee salary'!AI11 -> 7694500 | D6: 1030518500 | E6: Vietcombank - CN Tan Dinh | F6: HCM | G6: Lương tháng | H6: =$E$3 -> 05 2026
A7: 3 | B7: Đặng Quế Quyên | C7: ='Employee salary'!AI12 -> 3244500 | D7: 1030669566 | E7: Vietcombank - CN Sai gon | F7: HCM | G7: Lương tháng | H7: =$E$3 -> 05 2026
C8: =SUM(C6:C7) -> 10939000 | E8: ='Employee salary'!$Q$20 -> TP.HCM, Ngày 25 tháng 05 năm 2026
B10: LẬP BIỂU | D10: KIỂM TRA | F10: PHÊ DUYỆT
B11: PREPARED BY | D11: CHECKED BY | F11: APPROVED BY
F16: TÔN THẤT TRUNG KIÊN

Sheet Sealink Transfer
A1: stt (No) | B1: so ref (ref no) | C1: so tai khoan (beneficiary account) | D1: so cmnd (ID number) | E1: ngay cap (issued date) | F1: noi cap (issued place) | G1: ten nguoi huong (beneficiary name) | H1: ten ngan hang (bank name) | I1: so tien (amount) | J1: loai tien (currency) | K1: noi dung (content)
A2: 1 | C2: 0251001688536 | G2: TO TO VAN | H2: VIETCOMBANK | I2: 87578463 | J2: vnd | K2: payroll 08-22
A3: 2 | C3: 1030518500 | G3: NGUYEN LY TUONG | H3: VIETCOMBANK | I3: 5820454.3 | J3: vnd | K3: payroll 08-22
A4: 3 | C4: 1030669566 | G4: DANG QUE QUYEN | H4: VIETCOMBANK | I4: 4172727.6 | J4: vnd | K4: payroll 08-22
A5: 4 | C5: 0331000510942 | G5: NGUYEN THI NHU | H5: VIETCOMBANK | I5: 6586363.8 | J5: vnd | K5: payroll 08-22

Sheet Bank list
A1: No. | B1: Bank Code | C1: Bank Name
A2: 1 | B2: 01642001 | C2: TAIPEI FUBONC.B
A3: 2 | B3: 79632001 | C3: SINOPAC
A4: 3 | B4: 79635001 | C4: MALAYAN BANKING BERHAD - Chi nhánh TP. HCM
A5: 4 | B5: 79619001 | C5: DEUTSCHE BANK
A6: 5 | B6: 79601001 | C6: BPCE IOM
A7: 6 | B7: 79614001 | C7: BNP PARIBAS - Chi nhánh TP.HCM
A8: 7 | B8: 01657001 | C8: BNP PARIBAS - Chi nhánh Hà Nội
A9: 8 | B9: 79637001 | C9: (WOORI) Woori Bank - Chi nhánh TP.HCM
A10: 9 | B10: 01663001 | C10: (WOORI) Woori Bank
A11: 10 | B11: 01505001 | C11: (VRB) Liên doanh Việt Nga
A12: 11 | B12: 01309001 | C12: (VPBANK) Việt Nam Thịnh Vượng
... A166: 165 | B166: 46308001 | C166: NHTMCP Sai Gon Cong Thuong - CN Hue
